{
"mc": {
	"bullet03": {
		"frameRate":24,
		"labels": [
		],
		"frames": [
			{"res":"bullet030000","x":9.4,"y":-23.85},
			{"res":"bullet030001","x":9.4,"y":-31.85},
			{"res":"bullet030002","x":9.4,"y":-41.85},
			{"res":"bullet030003","x":9.4,"y":-55.85},
			{"res":"bullet030004","x":9.4,"y":-52.85},
			{"res":"bullet030005","x":9.4,"y":-60.85},
			{"res":"bullet030006","x":9.4,"y":-60.85},
			{"res":"bullet030007","x":9.4,"y":-58.85},
			{"res":"bullet030008","x":9.4,"y":-57.85},
			{"res":"bullet030009","x":9.4,"y":-60.85},
			{"res":"bullet030010","x":5.4,"y":-41.85},
			{"res":"bullet030011","x":27.4,"y":-34.85},
			{"res":"bullet030012","x":32.4,"y":-35.85},
			{"res":"bullet030013","x":55.4,"y":-52.85}
		]
	}
},
"res": {
	"bullet030000":{"x":451,"y":57,"w":42,"h":44},
	"bullet030001":{"x":451,"y":0,"w":56,"h":57},
	"bullet030002":{"x":0,"y":291,"w":84,"h":70},
	"bullet030003":{"x":140,"y":214,"w":111,"h":98},
	"bullet030004":{"x":0,"y":122,"w":140,"h":95},
	"bullet030005":{"x":150,"y":0,"w":157,"h":115},
	"bullet030006":{"x":0,"y":0,"w":150,"h":122},
	"bullet030007":{"x":307,"y":0,"w":144,"h":116},
	"bullet030008":{"x":150,"y":115,"w":152,"h":99},
	"bullet030009":{"x":302,"y":116,"w":153,"h":92},
	"bullet030010":{"x":302,"y":208,"w":157,"h":76},
	"bullet030011":{"x":0,"y":217,"w":121,"h":74},
	"bullet030012":{"x":341,"y":284,"w":116,"h":58},
	"bullet030013":{"x":251,"y":284,"w":90,"h":97}
}
}